MANIFEST.in
README.rst
alerts.json
setup.cfg
setup.py
tesouro_investor/__init__.py
tesouro_investor/alerter.py
tesouro_investor/cli.py
tesouro_investor/creat_db.py
tesouro_investor/scrapper.py
tesouro_investor.egg-info/PKG-INFO
tesouro_investor.egg-info/SOURCES.txt
tesouro_investor.egg-info/dependency_links.txt
tesouro_investor.egg-info/entry_points.txt
tesouro_investor.egg-info/requires.txt
tesouro_investor.egg-info/top_level.txt
tesouro_investor/emailSender/__init__.py
tesouro_investor/emailSender/sendMail.py