Metadata-Version: 1.1
Name: tesouro-investor
Version: 0.1.0a3
Summary: Support tool for Tesouro Direto investors
Home-page: https://github.com/fernandosjp/tesouro-investor
Author: Fernando Paiva
Author-email: fernandosjp@gmail.com
License: GPLv2
Keywords: finance
Platform: UNKNOWN
Classifier: Development Status :: 3 - Alpha
Classifier: Intended Audience :: Developers
Classifier: Intended Audience :: Financial and Insurance Industry
Classifier: Programming Language :: Python
Classifier: Topic :: Software Development :: Build Tools
Classifier: Topic :: Office/Business :: Financial :: Investment
Classifier: License :: OSI Approved :: GNU General Public License v2 (GPLv2)
Classifier: Programming Language :: Python :: 2
Classifier: Programming Language :: Python :: 2.6
Classifier: Programming Language :: Python :: 2.7
